infi.registry-0.1.21-py2.7-nspkg.pth
infi/registry/__init__.py
infi/registry/c_api.py
infi/registry/constants.py
infi/registry/dtypes.py
infi/registry/errors.py
infi/registry/funcs.py
infi/registry/key.py
infi/registry/test_datatypes.py
infi/registry/tests.py
infi/registry/value.py
infi/registry/interface/__init__.py
infi/registry/interface/tests.py
infi.registry-0.1.21.dist-info/LICENSE
infi.registry-0.1.21.dist-info/METADATA
infi.registry-0.1.21.dist-info/WHEEL
infi.registry-0.1.21.dist-info/entry_points.txt
infi.registry-0.1.21.dist-info/namespace_packages.txt
infi.registry-0.1.21.dist-info/top_level.txt
infi.registry-0.1.21.dist-info/RECORD
